{
  "data": [
    {
      "id": 3,
      "writer": "fasdf",
      "content": "asdfas",
      "date": "fsdafdsa"
    },
    {
      "id": 4,
      "writer": "fasdf",
      "content": "asdfas",
      "date": "fsdafdsa"
    },
    {
      "id": 5,
      "writer": "fasdf",
      "content": "asdfas",
      "date": "fsdafdsa"
    },
    {
      "id": 6,
      "writer": "fasdf",
      "content": "asdfas",
      "date": "fsdafdsa"
    },
    {
      "id": 7,
      "writer": "fsda",
      "content": "fdsafdsa",
      "date": "fdsa"
    },
    {
      "id": 8,
      "writer": "fsda",
      "content": "fdsafdsa",
      "date": "fdsa"
    }
  ]
}